{"date": "20121003", "stop_locations": [{"distance": 13333.00992851403, "direction": 1, "id_stop": 199}, {"distance": 22399.54862001703, "direction": 1, "id_stop": 440}, {"distance": 21333.510384358357, "direction": 1, "id_stop": 615}, {"distance": 24531.625091334376, "direction": 1, "id_stop": 1359}, {"distance": 26666.72360814419, "direction": 1, "id_stop": 1407}, {"distance": 23465.5868556757, "direction": 1, "id_stop": 1472}, {"distance": 0.0, "direction": 1, "id_stop": 1519}, {"distance": 25597.663326993046, "direction": 1, "id_stop": 1889}, {"distance": 15999.843413795472, "direction": 1, "id_stop": 2055}, {"distance": 5330.434648104152, "direction": 1, "id_stop": 2550}, {"distance": 5334.547676302089, "direction": 1, "id_stop": 2771}, {"distance": 26663.70156265172, "direction": 1, "id_stop": 2788}, {"distance": 5336.067879046257, "direction": 1, "id_stop": 2795}, {"distance": 0.0, "direction": 0, "id_stop": 488}, {"distance": 0.0, "direction": 0, "id_stop": 547}, {"distance": 0.0, "direction": 0, "id_stop": 586}, {"distance": 0.0, "direction": 0, "id_stop": 1660}, {"distance": 0.0, "direction": 0, "id_stop": 1666}, {"distance": 0.0, "direction": 0, "id_stop": 2005}, {"distance": 0.0, "direction": 0, "id_stop": 2950}, {"distance": 0.0, "direction": 0, "id_stop": 3044}, {"distance": 0.0, "direction": -1, "id_stop": 3026}], "id_route": "5", "trips": [{"id_trip": "19098", "trip_direction": 0, "stops": [{"count": 5, "count_exiting": 0, "count_boarding": 5, "time_departure": 1349241460, "time_arrival": 1349241460, "id_stop": 2950}, {"count": 5, "count_exiting": 0, "count_boarding": 0, "time_departure": 1349241596, "time_arrival": 1349241478, "id_stop": 586}, {"count": 3, "count_exiting": 3, "count_boarding": 1, "time_departure": 1349241679, "time_arrival": 1349241667, "id_stop": 1660}, {"count": 3, "count_exiting": 0, "count_boarding": 0, "time_departure": 1349241762, "time_arrival": 1349241758, "id_stop": 2005}, {"count": 2, "count_exiting": 1, "count_boarding": 0, "time_departure": 1349241823, "time_arrival": 1349241816, "id_stop": 3044}, {"count": 2, "count_exiting": 0, "count_boarding": 0, "time_departure": 1349241900, "time_arrival": 1349241898, "id_stop": 488}, {"count": 2, "count_exiting": 0, "count_boarding": 0, "time_departure": 1349241971, "time_arrival": 1349241970, "id_stop": 547}, {"count": 2, "count_exiting": 0, "count_boarding": 0, "time_departure": 1349242087, "time_arrival": 1349242085, "id_stop": 1666}, {"count": 0, "count_exiting": 2, "count_boarding": 0, "time_departure": 1349242311, "time_arrival": 1349242223, "id_stop": 3026}]}, {"id_trip": "19830", "trip_direction": 1, "stops": [{"count": 7, "count_exiting": 0, "count_boarding": 7, "time_departure": 1349242335, "time_arrival": 1349242335, "id_stop": 3026}, {"count": 7, "count_exiting": 0, "count_boarding": 0, "time_departure": 1349242420, "time_arrival": 1349242417, "id_stop": 2055}, {"count": 7, "count_exiting": 0, "count_boarding": 0, "time_departure": 1349242526, "time_arrival": 1349242525, "id_stop": 615}, {"count": 9, "count_exiting": 2, "count_boarding": 4, "time_departure": 1349242599, "time_arrival": 1349242587, "id_stop": 440}, {"count": 11, "count_exiting": 0, "count_boarding": 2, "time_departure": 1349242695, "time_arrival": 1349242683, "id_stop": 1472}, {"count": 9, "count_exiting": 2, "count_boarding": 0, "time_departure": 1349242765, "time_arrival": 1349242756, "id_stop": 1359}, {"count": 1, "count_exiting": 8, "count_boarding": 0, "time_departure": 1349242885, "time_arrival": 1349242870, "id_stop": 1889}, {"count": 0, "count_exiting": 1, "count_boarding": 0, "time_departure": 1349242985, "time_arrival": 1349242977, "id_stop": 2788}, {"count": 0, "count_exiting": 0, "count_boarding": 0, "time_departure": 1349243790, "time_arrival": 1349243084, "id_stop": 1407}]}, {"id_trip": "22830", "trip_direction": 1, "stops": [{"count": 0, "count_exiting": 0, "count_boarding": 0, "time_departure": 1349245258, "time_arrival": 1349245258, "id_stop": 1519}, {"count": 0, "count_exiting": 0, "count_boarding": 0, "time_departure": 1349245321, "time_arrival": 1349245311, "id_stop": 1519}, {"count": 7, "count_exiting": 0, "count_boarding": 7, "time_departure": 1349245383, "time_arrival": 1349245373, "id_stop": 2550}, {"count": 8, "count_exiting": 0, "count_boarding": 1, "time_departure": 1349245465, "time_arrival": 1349245454, "id_stop": 2771}, {"count": 9, "count_exiting": 0, "count_boarding": 1, "time_departure": 1349245565, "time_arrival": 1349245557, "id_stop": 2795}, {"count": 6, "count_exiting": 3, "count_boarding": 0, "time_departure": 1349245634, "time_arrival": 1349245623, "id_stop": 199}, {"count": 22, "count_exiting": 0, "count_boarding": 16, "time_departure": 1349245749, "time_arrival": 1349245709, "id_stop": 3026}, {"count": 21, "count_exiting": 1, "count_boarding": 0, "time_departure": 1349245845, "time_arrival": 1349245837, "id_stop": 2055}, {"count": 23, "count_exiting": 1, "count_boarding": 3, "time_departure": 1349246019, "time_arrival": 1349245969, "id_stop": 615}, {"count": 23, "count_exiting": 11, "count_boarding": 11, "time_departure": 1349246161, "time_arrival": 1349246142, "id_stop": 440}, {"count": 25, "count_exiting": 2, "count_boarding": 4, "time_departure": 1349246265, "time_arrival": 1349246251, "id_stop": 1472}, {"count": 24, "count_exiting": 1, "count_boarding": 0, "time_departure": 1349246336, "time_arrival": 1349246329, "id_stop": 1359}, {"count": 8, "count_exiting": 16, "count_boarding": 0, "time_departure": 1349246441, "time_arrival": 1349246427, "id_stop": 1889}, {"count": 5, "count_exiting": 3, "count_boarding": 0, "time_departure": 1349246540, "time_arrival": 1349246529, "id_stop": 2788}, {"count": 0, "count_exiting": 5, "count_boarding": 0, "time_departure": 1349246652, "time_arrival": 1349246637, "id_stop": 1407}]}, {"id_trip": "25890", "trip_direction": 1, "stops": [{"count": 2, "count_exiting": 0, "count_boarding": 2, "time_departure": 1349248302, "time_arrival": 1349248302, "id_stop": 1519}, {"count": 2, "count_exiting": 0, "count_boarding": 2, "time_departure": 1349248358, "time_arrival": 1349248345, "id_stop": 1519}, {"count": 14, "count_exiting": 0, "count_boarding": 12, "time_departure": 1349248416, "time_arrival": 1349248403, "id_stop": 2550}, {"count": 18, "count_exiting": 1, "count_boarding": 5, "time_departure": 1349248497, "time_arrival": 1349248480, "id_stop": 2771}, {"count": 31, "count_exiting": 0, "count_boarding": 13, "time_departure": 1349248585, "time_arrival": 1349248570, "id_stop": 2795}, {"count": 63, "count_exiting": 13, "count_boarding": 45, "time_departure": 1349248669, "time_arrival": 1349248647, "id_stop": 199}, {"count": 172, "count_exiting": 5, "count_boarding": 114, "time_departure": 1349248812, "time_arrival": 1349248741, "id_stop": 3026}, {"count": 171, "count_exiting": 2, "count_boarding": 1, "time_departure": 1349248908, "time_arrival": 1349248898, "id_stop": 2055}, {"count": 167, "count_exiting": 14, "count_boarding": 10, "time_departure": 1349249048, "time_arrival": 1349249029, "id_stop": 615}, {"count": 185, "count_exiting": 80, "count_boarding": 98, "time_departure": 1349249168, "time_arrival": 1349249114, "id_stop": 440}, {"count": 180, "count_exiting": 26, "count_boarding": 21, "time_departure": 1349249295, "time_arrival": 1349249262, "id_stop": 1472}, {"count": 83, "count_exiting": 114, "count_boarding": 17, "time_departure": 1349249388, "time_arrival": 1349249346, "id_stop": 1359}, {"count": 31, "count_exiting": 53, "count_boarding": 1, "time_departure": 1349249530, "time_arrival": 1349249508, "id_stop": 1889}, {"count": 17, "count_exiting": 14, "count_boarding": 0, "time_departure": 1349249623, "time_arrival": 1349249611, "id_stop": 2788}, {"count": 0, "count_exiting": 17, "count_boarding": 0, "time_departure": 1349250022, "time_arrival": 1349249713, "id_stop": 1407}]}, {"id_trip": "29490", "trip_direction": 1, "stops": [{"count": 7, "count_exiting": 0, "count_boarding": 7, "time_departure": 1349251903, "time_arrival": 1349251903, "id_stop": 1519}, {"count": 7, "count_exiting": 0, "count_boarding": 7, "time_departure": 1349251954, "time_arrival": 1349251944, "id_stop": 1519}, {"count": 14, "count_exiting": 0, "count_boarding": 7, "time_departure": 1349252007, "time_arrival": 1349251997, "id_stop": 2550}, {"count": 23, "count_exiting": 0, "count_boarding": 9, "time_departure": 1349252089, "time_arrival": 1349252073, "id_stop": 2771}, {"count": 36, "count_exiting": 0, "count_boarding": 13, "time_departure": 1349252191, "time_arrival": 1349252177, "id_stop": 2795}, {"count": 37, "count_exiting": 12, "count_boarding": 13, "time_departure": 1349252289, "time_arrival": 1349252269, "id_stop": 199}, {"count": 129, "count_exiting": 3, "count_boarding": 95, "time_departure": 1349252392, "time_arrival": 1349252360, "id_stop": 3026}, {"count": 132, "count_exiting": 3, "count_boarding": 6, "time_departure": 1349252510, "time_arrival": 1349252493, "id_stop": 2055}, {"count": 123, "count_exiting": 10, "count_boarding": 1, "time_departure": 1349252637, "time_arrival": 1349252624, "id_stop": 615}, {"count": 141, "count_exiting": 78, "count_boarding": 96, "time_departure": 1349252777, "time_arrival": 1349252712, "id_stop": 440}, {"count": 132, "count_exiting": 13, "count_boarding": 4, "time_departure": 1349252890, "time_arrival": 1349252869, "id_stop": 1472}, {"count": 75, "count_exiting": 59, "count_boarding": 2, "time_departure": 1349252980, "time_arrival": 1349252953, "id_stop": 1359}, {"count": 61, "count_exiting": 14, "count_boarding": 0, "time_departure": 1349253082, "time_arrival": 1349253069, "id_stop": 1889}, {"count": 53, "count_exiting": 10, "count_boarding": 2, "time_departure": 1349253176, "time_arrival": 1349253160, "id_stop": 2788}, {"count": 0, "count_exiting": 53, "count_boarding": 0, "time_departure": 1349253649, "time_arrival": 1349253262, "id_stop": 1407}]}, {"id_trip": "32700", "trip_direction": 1, "stops": [{"count": 0, "count_exiting": 0, "count_boarding": 0, "time_departure": 1349255231, "time_arrival": 1349255231, "id_stop": 1519}, {"count": 0, "count_exiting": 0, "count_boarding": 0, "time_departure": 1349255295, "time_arrival": 1349255285, "id_stop": 1519}, {"count": 5, "count_exiting": 0, "count_boarding": 5, "time_departure": 1349255367, "time_arrival": 1349255351, "id_stop": 2550}, {"count": 12, "count_exiting": 0, "count_boarding": 7, "time_departure": 1349255466, "time_arrival": 1349255448, "id_stop": 2771}, {"count": 16, "count_exiting": 0, "count_boarding": 4, "time_departure": 1349255566, "time_arrival": 1349255551, "id_stop": 2795}, {"count": 20, "count_exiting": 3, "count_boarding": 7, "time_departure": 1349255643, "time_arrival": 1349255631, "id_stop": 199}, {"count": 48, "count_exiting": 3, "count_boarding": 31, "time_departure": 1349255733, "time_arrival": 1349255715, "id_stop": 3026}, {"count": 52, "count_exiting": 0, "count_boarding": 4, "time_departure": 1349255839, "time_arrival": 1349255824, "id_stop": 2055}, {"count": 50, "count_exiting": 2, "count_boarding": 0, "time_departure": 1349255966, "time_arrival": 1349255955, "id_stop": 615}, {"count": 32, "count_exiting": 27, "count_boarding": 9, "time_departure": 1349256070, "time_arrival": 1349256046, "id_stop": 440}, {"count": 28, "count_exiting": 10, "count_boarding": 6, "time_departure": 1349256226, "time_arrival": 1349256209, "id_stop": 1472}, {"count": 17, "count_exiting": 11, "count_boarding": 0, "time_departure": 1349256290, "time_arrival": 1349256278, "id_stop": 1359}, {"count": 9, "count_exiting": 8, "count_boarding": 0, "time_departure": 1349256404, "time_arrival": 1349256388, "id_stop": 1889}, {"count": 5, "count_exiting": 4, "count_boarding": 0, "time_departure": 1349256501, "time_arrival": 1349256491, "id_stop": 2788}, {"count": 0, "count_exiting": 5, "count_boarding": 0, "time_departure": 1349256777, "time_arrival": 1349256599, "id_stop": 1407}]}, {"id_trip": "42150", "trip_direction": 1, "stops": [{"count": 1, "count_exiting": 0, "count_boarding": 1, "time_departure": 1349264579, "time_arrival": 1349264579, "id_stop": 1519}, {"count": 1, "count_exiting": 0, "count_boarding": 1, "time_departure": 1349264634, "time_arrival": 1349264619, "id_stop": 1519}, {"count": 10, "count_exiting": 1, "count_boarding": 10, "time_departure": 1349264691, "time_arrival": 1349264678, "id_stop": 2550}, {"count": 15, "count_exiting": 4, "count_boarding": 9, "time_departure": 1349264777, "time_arrival": 1349264763, "id_stop": 2771}, {"count": 19, "count_exiting": 0, "count_boarding": 4, "time_departure": 1349264863, "time_arrival": 1349264848, "id_stop": 2795}, {"count": 16, "count_exiting": 9, "count_boarding": 6, "time_departure": 1349264933, "time_arrival": 1349264916, "id_stop": 199}, {"count": 39, "count_exiting": 2, "count_boarding": 25, "time_departure": 1349265025, "time_arrival": 1349265005, "id_stop": 3026}, {"count": 56, "count_exiting": 0, "count_boarding": 17, "time_departure": 1349265115, "time_arrival": 1349265096, "id_stop": 2055}, {"count": 49, "count_exiting": 10, "count_boarding": 3, "time_departure": 1349265242, "time_arrival": 1349265225, "id_stop": 615}, {"count": 46, "count_exiting": 35, "count_boarding": 32, "time_departure": 1349265345, "time_arrival": 1349265315, "id_stop": 440}, {"count": 53, "count_exiting": 4, "count_boarding": 11, "time_departure": 1349265506, "time_arrival": 1349265473, "id_stop": 1472}, {"count": 24, "count_exiting": 31, "count_boarding": 2, "time_departure": 1349265575, "time_arrival": 1349265558, "id_stop": 1359}, {"count": 18, "count_exiting": 11, "count_boarding": 5, "time_departure": 1349265699, "time_arrival": 1349265683, "id_stop": 1889}, {"count": 26, "count_exiting": 1, "count_boarding": 9, "time_departure": 1349265799, "time_arrival": 1349265785, "id_stop": 2788}, {"count": 0, "count_exiting": 26, "count_boarding": 0, "time_departure": 1349266227, "time_arrival": 1349265894, "id_stop": 1407}]}, {"id_trip": "58200", "trip_direction": 1, "stops": [{"count": 0, "count_exiting": 0, "count_boarding": 0, "time_departure": 1349280614, "time_arrival": 1349280614, "id_stop": 1519}, {"count": 0, "count_exiting": 0, "count_boarding": 0, "time_departure": 1349280671, "time_arrival": 1349280658, "id_stop": 1519}, {"count": 9, "count_exiting": 0, "count_boarding": 9, "time_departure": 1349280725, "time_arrival": 1349280712, "id_stop": 2550}, {"count": 31, "count_exiting": 1, "count_boarding": 23, "time_departure": 1349280814, "time_arrival": 1349280794, "id_stop": 2771}, {"count": 36, "count_exiting": 0, "count_boarding": 5, "time_departure": 1349280917, "time_arrival": 1349280904, "id_stop": 2795}, {"count": 28, "count_exiting": 9, "count_boarding": 1, "time_departure": 1349280994, "time_arrival": 1349280975, "id_stop": 199}, {"count": 32, "count_exiting": 8, "count_boarding": 12, "time_departure": 1349281115, "time_arrival": 1349281068, "id_stop": 3026}, {"count": 43, "count_exiting": 0, "count_boarding": 11, "time_departure": 1349281219, "time_arrival": 1349281207, "id_stop": 2055}, {"count": 39, "count_exiting": 5, "count_boarding": 1, "time_departure": 1349281348, "time_arrival": 1349281337, "id_stop": 615}, {"count": 18, "count_exiting": 29, "count_boarding": 8, "time_departure": 1349281441, "time_arrival": 1349281423, "id_stop": 440}, {"count": 16, "count_exiting": 6, "count_boarding": 4, "time_departure": 1349281666, "time_arrival": 1349281652, "id_stop": 1472}, {"count": 15, "count_exiting": 2, "count_boarding": 1, "time_departure": 1349281747, "time_arrival": 1349281736, "id_stop": 1359}, {"count": 11, "count_exiting": 7, "count_boarding": 3, "time_departure": 1349281862, "time_arrival": 1349281849, "id_stop": 1889}, {"count": 12, "count_exiting": 1, "count_boarding": 2, "time_departure": 1349281960, "time_arrival": 1349281950, "id_stop": 2788}, {"count": 0, "count_exiting": 12, "count_boarding": 0, "time_departure": 1349282324, "time_arrival": 1349282064, "id_stop": 1407}]}, {"id_trip": "61800", "trip_direction": 1, "stops": [{"count": 4, "count_exiting": 0, "count_boarding": 4, "time_departure": 1349284235, "time_arrival": 1349284235, "id_stop": 1519}, {"count": 4, "count_exiting": 0, "count_boarding": 4, "time_departure": 1349284288, "time_arrival": 1349284274, "id_stop": 1519}, {"count": 30, "count_exiting": 0, "count_boarding": 26, "time_departure": 1349284359, "time_arrival": 1349284336, "id_stop": 2550}, {"count": 67, "count_exiting": 1, "count_boarding": 38, "time_departure": 1349284441, "time_arrival": 1349284424, "id_stop": 2771}, {"count": 79, "count_exiting": 1, "count_boarding": 13, "time_departure": 1349284536, "time_arrival": 1349284519, "id_stop": 2795}, {"count": 60, "count_exiting": 22, "count_boarding": 3, "time_departure": 1349284606, "time_arrival": 1349284589, "id_stop": 199}, {"count": 96, "count_exiting": 15, "count_boarding": 51, "time_departure": 1349284709, "time_arrival": 1349284670, "id_stop": 3026}, {"count": 128, "count_exiting": 4, "count_boarding": 36, "time_departure": 1349284833, "time_arrival": 1349284809, "id_stop": 2055}, {"count": 129, "count_exiting": 6, "count_boarding": 7, "time_departure": 1349284995, "time_arrival": 1349284982, "id_stop": 615}, {"count": 34, "count_exiting": 118, "count_boarding": 23, "time_departure": 1349285094, "time_arrival": 1349285059, "id_stop": 440}, {"count": 33, "count_exiting": 12, "count_boarding": 11, "time_departure": 1349285252, "time_arrival": 1349285236, "id_stop": 1472}, {"count": 28, "count_exiting": 6, "count_boarding": 1, "time_departure": 1349285335, "time_arrival": 1349285323, "id_stop": 1359}, {"count": 25, "count_exiting": 6, "count_boarding": 3, "time_departure": 1349285459, "time_arrival": 1349285446, "id_stop": 1889}, {"count": 25, "count_exiting": 1, "count_boarding": 1, "time_departure": 1349285554, "time_arrival": 1349285542, "id_stop": 2788}, {"count": 0, "count_exiting": 25, "count_boarding": 0, "time_departure": 1349285918, "time_arrival": 1349285663, "id_stop": 1407}]}, {"id_trip": "65400", "trip_direction": 1, "stops": [{"count": 2, "count_exiting": 0, "count_boarding": 2, "time_departure": 1349287817, "time_arrival": 1349287817, "id_stop": 1519}, {"count": 2, "count_exiting": 0, "count_boarding": 2, "time_departure": 1349287869, "time_arrival": 1349287857, "id_stop": 1519}, {"count": 27, "count_exiting": 0, "count_boarding": 25, "time_departure": 1349287930, "time_arrival": 1349287912, "id_stop": 2550}, {"count": 59, "count_exiting": 1, "count_boarding": 33, "time_departure": 1349288012, "time_arrival": 1349287992, "id_stop": 2771}, {"count": 65, "count_exiting": 1, "count_boarding": 7, "time_departure": 1349288096, "time_arrival": 1349288083, "id_stop": 2795}, {"count": 52, "count_exiting": 24, "count_boarding": 11, "time_departure": 1349288165, "time_arrival": 1349288147, "id_stop": 199}, {"count": 84, "count_exiting": 5, "count_boarding": 37, "time_departure": 1349288251, "time_arrival": 1349288227, "id_stop": 3026}, {"count": 101, "count_exiting": 4, "count_boarding": 21, "time_departure": 1349288337, "time_arrival": 1349288319, "id_stop": 2055}, {"count": 96, "count_exiting": 12, "count_boarding": 7, "time_departure": 1349288496, "time_arrival": 1349288476, "id_stop": 615}, {"count": 35, "count_exiting": 76, "count_boarding": 15, "time_departure": 1349288653, "time_arrival": 1349288623, "id_stop": 440}, {"count": 18, "count_exiting": 19, "count_boarding": 2, "time_departure": 1349288786, "time_arrival": 1349288772, "id_stop": 1472}, {"count": 12, "count_exiting": 7, "count_boarding": 1, "time_departure": 1349288866, "time_arrival": 1349288853, "id_stop": 1359}, {"count": 13, "count_exiting": 2, "count_boarding": 3, "time_departure": 1349288974, "time_arrival": 1349288959, "id_stop": 1889}, {"count": 14, "count_exiting": 2, "count_boarding": 3, "time_departure": 1349289078, "time_arrival": 1349289060, "id_stop": 2788}, {"count": 0, "count_exiting": 14, "count_boarding": 0, "time_departure": 1349289578, "time_arrival": 1349289185, "id_stop": 1407}]}]}